<?xml version="1.0" encoding="ISO-8859-1"?>

<PropertyList>
    
    <path>PHI-Doppler.ac</path>
    
    <effect>
        <inherits-from>Aircraft/G91-R1B_HD/Models/Effects/Reflections/reflection_black_00</inherits-from>
        <object-name>box (Meshed)</object-name>
        <object-name>box_cover_inf (Meshed)</object-name>
        <object-name>top (Meshed)</object-name>
        <object-name>screews_m5 (Meshed)</object-name>
        <object-name>lamp_ring (Meshed)</object-name>
        <object-name>labels (Meshed)</object-name>
        <object-name>top_light (Meshed)</object-name>
        <object-name>cover_lamp1 (Meshed)</object-name>
        <object-name>cover_lamp2 (Meshed)</object-name>
        <object-name>switch_3 (Meshed)</object-name>
        <object-name>switch_1_ring (Meshed)</object-name>
        <object-name>switch_1_cone (Meshed)</object-name>
        <object-name>switch_1_level (Meshed)</object-name>
        <object-name>switch_2_ring (Meshed)</object-name>
        <object-name>switch_2_cone (Meshed)</object-name>
        <object-name>switch_2_level (Meshed)</object-name>
    </effect>
    
    <effect>
        <inherits-from>Aircraft/G91-R1B_HD/Models/Effects/Interior_Shading/Interior_Shading</inherits-from>
        <object-name>box (Meshed)</object-name>
        <object-name>box_cover_inf (Meshed)</object-name>
        <object-name>top (Meshed)</object-name>
        <object-name>screews_m5 (Meshed)</object-name>
        <object-name>push take control (Meshed)</object-name>
        <object-name>labels (Meshed)</object-name>
        <object-name>lamp_ring (Meshed)</object-name>
        <object-name>top_light (Meshed)</object-name>
        <object-name>cover_lamp1 (Meshed)</object-name>
        <object-name>cover_lamp2 (Meshed)</object-name>
        <object-name>switch_3 (Meshed)</object-name>
        <object-name>switch_1_ring (Meshed)</object-name>
        <object-name>switch_1_cone (Meshed)</object-name>
        <object-name>switch_1_level (Meshed)</object-name>
        <object-name>switch_2_ring (Meshed)</object-name>
        <object-name>switch_2_cone (Meshed)</object-name>
        <object-name>switch_2_level (Meshed)</object-name>
    </effect>

    <effect>
        <inherits-from>Effects/model-transparent</inherits-from>
        <object-name>lamp_glass (Meshed)</object-name>
        <object-name>switch_2_decrease (Meshed)</object-name>   
        <object-name>switch_2_increase (Meshed)</object-name>   
        <object-name>switch_2_left (Meshed)</object-name>  
        <object-name>switch_2_right (Meshed)</object-name>
    </effect>
    
    <animation> 
        <type>material</type>
        <object-name>box (Meshed)</object-name> 
        <texture>Pictures/G91-Yello01.png</texture>
        <ambient>
            <red>0.6</red>
            <green>0.6</green>
            <blue>0.6</blue>
        </ambient>
    </animation>
    
    <animation> 
        <type>material</type>
        <texture>Pictures/G91-Al-dark.png</texture>
        <object-name>screews_m5 (Meshed)</object-name>
        <ambient>
            <red>0.3</red>
            <green>0.3</green>
            <blue>0.3</blue>
        </ambient>
        <emission>
            <red>0.10</red>
            <green>0.0</green>
            <blue>0.0</blue>
            <factor-prop>sim/G91/re_emit/gauge_red_light</factor-prop>
        </emission>
    </animation>
    
    <animation> 
        <type>material</type>
        <texture>Pictures/G91-Dark-Grey.png</texture>
        <object-name>box_cover_inf (Meshed)</object-name>
        <ambient>
            <red>0.1</red>
            <green>0.1</green>
            <blue>0.1</blue>
        </ambient>
        <emission>
            <red>0.15</red>
            <green>0.0</green>
            <blue>0.0</blue>
            <factor-prop>sim/G91/re_emit/gauge_red_light</factor-prop>
        </emission>
    </animation>
    
    <animation> 
        <type>material</type>
        <texture>Pictures/G91-Dark-Grey.png</texture>
        <object-name>box_cover_inf (Meshed)</object-name>
        <ambient>
            <red>0.5</red>
            <green>0.5</green>
            <blue>0.5</blue>
        </ambient>
        <emission>
            <red>0.35</red>
            <green>0.0</green>
            <blue>0.0</blue>
            <factor-prop>sim/G91/re_emit/gauge_red_light</factor-prop>
        </emission>
    </animation>
    
    <animation> 
        <type>material</type>
        <texture>Pictures/G91-Dark-Grey.png</texture>
        <object-name>top (Meshed)</object-name>
        <ambient>
            <red>0.4</red>
            <green>0.4</green>
            <blue>0.4</blue>
        </ambient>
        <emission>
            <red>0.35</red>
            <green>0.0</green>
            <blue>0.0</blue>
            <factor-prop>sim/G91/re_emit/gauge_red_light</factor-prop>
        </emission>
        <specular>
            <red>0.7</red>
            <green>0.7</green>
            <blue>0.7</blue>
        </specular>
    </animation>
    
    <animation> 
        <type>material</type>
        <texture>Pictures/Pictures/G91-Black.png</texture>
        <object-name>cover_lamp1 (Meshed)</object-name>
        <object-name>cover_lamp2 (Meshed)</object-name>
        <ambient>
            <red>0.6</red>
            <green>0.6</green>
            <blue>0.6</blue>
        </ambient>
        <emission>
            <red>0.35</red>
            <green>0.0</green>
            <blue>0.0</blue>
            <factor-prop>sim/G91/re_emit/gauge_red_light</factor-prop>
        </emission>
    </animation>
    
    <animation> 
        <type>material</type>
        <texture>Pictures/G91-Ivory.png</texture>
        <object-name>top_light (Meshed)</object-name>
        <ambient>
            <red>0.4</red>
            <green>0.45</green>
            <blue>0.4</blue>
        </ambient>
        <emission>
            <red>0.35</red>
            <green>0.12</green>
            <blue>0.0</blue>
            <factor-prop>sim/G91/re_emit/gauge_phosphorescent_light</factor-prop>
        </emission>
        <specular>
            <red>0.7</red>
            <green>0.7</green>
            <blue>0.7</blue>
        </specular>
    </animation>
    
    <animation> 
        <type>material</type>
        <texture>Pictures/G91-Al.png</texture>
        <object-name>lamp_ring (Meshed)</object-name>
        <ambient>
            <red>0.2</red>
            <green>0.2</green>
            <blue>0.2</blue>
        </ambient>
        <emission>
            <red>0.10</red>
            <green>0.0</green>
            <blue>0.0</blue>
            <factor-prop>sim/G91/re_emit/gauge_red_light</factor-prop>
        </emission>
        <specular>
            <red>0.7</red>
            <green>0.7</green>
            <blue>0.7</blue>
        </specular>
    </animation>
    
    <animation> 
        <type>material</type>
        <object-name>lamp_glass (Meshed)</object-name>
        <texture>Pictures/G91-Yellow_01.png</texture>
        <transparency>
            <alpha>1.0</alpha>
            <factor-prop>/fdm/jsbsim/systems/gauges/PHI/doppler/advise-light-transparent</factor-prop>
        </transparency>
        <ambient>
            <red>0.1</red>
            <green>0.05</green>
            <blue>0.0</blue>
        </ambient>
        <emission>
            <red>0.2</red>
            <green>0.0</green>
            <blue>0.0</blue>
            <factor-prop>sim/G91/re_emit/gauge_red_light</factor-prop>
        </emission>
        <specular>
            <red>0.5</red>
            <green>0.0</green>
            <blue>0.0</blue>
        </specular>
    </animation>

    <animation> 
        <type>material</type>
        <object-name>lamp_mirror (Meshed)</object-name>
        <texture>Pictures/G91-Orange01.png</texture>
        <ambient>
            <red>1.0</red>
            <green>0.5</green>
            <blue>0.0</blue>
        </ambient>
        <emission>
            <red>1.0</red>
            <green>0.5</green>
            <blue>0.0</blue>
            <factor-prop>/fdm/jsbsim/systems/gauges/PHI/doppler/advise-light-on</factor-prop>
        </emission>
    </animation>

    <animation> 
        <type>material</type>
        <object-name>lamp_light (Meshed)</object-name>
        <texture>Pictures/G91-Al-Light.png</texture>
        <transparency>
            <alpha>0.5</alpha>
        </transparency>
        <ambient>
            <red>0.0</red>
            <green>0.0</green>
            <blue>0.0</blue>
        </ambient>
        <emission>
            <red>1.0</red>
            <green>0.5</green>
            <blue>0.0</blue>
            <factor-prop>/fdm/jsbsim/systems/gauges/PHI/doppler/advise-light-on</factor-prop>
        </emission>
    </animation>
    
    <model>
        <condition>
            <greater-than-equals>
                <property>/fdm/jsbsim/systems/gauges/PHI/doppler/advise-light-on</property>
                <value>0.1</value>
            </greater-than-equals>
        </condition>
        <name>PHI_wind_advise_light_on</name>
        <path>procedural_light_PHI_yellow.xml</path>
        <offsets>
            <x-m> 0.015</x-m>
            <y-m> -0.035 </y-m>
            <z-m> 0.03 </z-m>
            <pitch-deg>-180</pitch-deg>
        </offsets>
    </model>
    
    <animation> 
        <type>material</type>
        <object-name>switch_2_decrease (Meshed)</object-name>   
        <object-name>switch_2_increase (Meshed)</object-name>   
        <object-name>switch_2_left (Meshed)</object-name>  
        <object-name>switch_2_right (Meshed)</object-name>
        <transparency>
            <alpha>0.0</alpha>
        </transparency>
    </animation>
  
    <animation> 
        <type>material</type>
        <object-name>switch_1_level (Meshed)</object-name>
        <object-name>switch_2_level (Meshed)</object-name>
        <texture>Pictures/G91-Al-Light.png</texture>
        <ambient>
            <red>0.8</red>
            <green>0.8</green>
            <blue>0.8</blue>
        </ambient>
        <emission>
            <red>0.15</red>
            <green>0.0</green>
            <blue>0.0</blue>
            <factor-prop>sim/G91/re_emit/gauge_red_light</factor-prop>
        </emission>
        <specular>
            <red>0.8</red>
            <green>0.9</green>
            <blue>0.9</blue>
        </specular>
    </animation>
    
    <animation> 
        <type>material</type>
        <object-name>switch_1_cone (Meshed)</object-name>
        <object-name>switch_2_cone (Meshed)</object-name>
        <texture>Pictures/G91-Al-Light.png</texture>
        <ambient>
            <red>0.5</red>
            <green>0.5</green>
            <blue>0.5</blue>
        </ambient>
        <emission>
            <red>0.1</red>
            <green>0.0</green>
            <blue>0.0</blue>
            <factor-prop>sim/G91/re_emit/gauge_red_light</factor-prop>
        </emission>
        <specular>
            <red>0.8</red>
            <green>0.9</green>
            <blue>0.9</blue>
        </specular>
    </animation>
    
    <animation> 
        <type>material</type>
        <object-name>switch_1_ring (Meshed)</object-name>
        <object-name>switch_2_ring (Meshed)</object-name>
        <texture>Pictures/G91-Al-Light.png</texture>
        <ambient>
            <red>0.2</red>
            <green>0.2</green>
            <blue>0.2</blue>
        </ambient>
        <emission>
            <red>0.1</red>
            <green>0.0</green>
            <blue>0.0</blue>
            <factor-prop>sim/G91/re_emit/gauge_red_light</factor-prop>
        </emission>
        <specular>
            <red>0.8</red>
            <green>0.9</green>
            <blue>0.9</blue>
        </specular>
    </animation>
    
    
    <animation> 
        <type>material</type>
        <object-name>switch_3 (Meshed)</object-name>
        <texture>Pictures/G91-Al-dark.png</texture>
        <ambient>
            <red>0.5</red>
            <green>0.5</green>
            <blue>0.5</blue>
        </ambient>
        <emission>
            <red>0.20</red>
            <green>0.0</green>
            <blue>0.0</blue>
            <factor-prop>sim/G91/re_emit/gauge_red_light</factor-prop>
        </emission>
        <specular>
            <red>0.8</red>
            <green>0.9</green>
            <blue>0.9</blue>
        </specular>
    </animation>
    
    <animation> 
        <type>material</type>
        <object-name>switch_3_green (Meshed)</object-name>
        <texture>Pictures/G91-Ivory.png</texture>
        <ambient>
            <red>0.4</red>
            <green>0.45</green>
            <blue>0.4</blue>
        </ambient>
        <emission>
            <red>0.0</red>
            <green>0.15</green>
            <blue>0.0</blue>
            <factor-prop>sim/G91/re_emit/gauge_phosphorescent_light</factor-prop>
        </emission>
        <specular>
            <red>0.7</red>
            <green>0.7</green>
            <blue>0.7</blue>
        </specular>
    </animation>
    
    <!-- Animations -->
    
    <animation>
        <type>knob</type>
        <object-name>switch_3 (Meshed)</object-name>
        <action>
            <button>0</button>
            <binding>
                <command>property-adjust</command>
                <property>fdm/jsbsim/systems/gauges/PHI/doppler/switch-turn</property>
                <factor>0.25</factor>
                <min>0</min>
                <max>3</max>                
                <wrap>false</wrap>
            </binding>
        </action>
    </animation>
    
    <animation>
        <type>rotate</type>
        <object-name>switch_3 (Meshed)</object-name>
        <object-name>switch_3_green (Meshed)</object-name>
        <property>fdm/jsbsim/systems/gauges/PHI/doppler/switch-turned</property>
        <factor>30</factor>
        <offset-deg>-45.0</offset-deg>
        <center>
            <x-m>0.0225</x-m>
            <y-m>-0.115</y-m>
            <z-m>0.0</z-m>
        </center>
        <axis>
            <x>0</x>
            <y>0</y>
            <z>-1</z>
        </axis>
    </animation>
    
    <animation>
        <type>translate</type>
        <object-name>switch_3 (Meshed)</object-name>
        <object-name>switch_3_green (Meshed)</object-name>
        <property>fdm/jsbsim/systems/gauges/PHI/doppler/switch-up</property>
        <factor>0.005</factor>
        <axis>
            <x>0</x>
            <y>0</y>
            <z>1</z>
        </axis>
    </animation>
    
    <animation>
        <type>pick</type>
        <visible>true</visible>
        <object-name>switch_1_level (Meshed)</object-name>
        <object-name>switch_1_ring (Meshed)</object-name>
        <action>
            <button>0</button>
            <repeatable>false</repeatable>
            <binding>
                <command>property-toggle</command>
                <property>fdm/jsbsim/systems/gauges/PHI/doppler/switch-terrain-sea</property>
            </binding>
        </action>
    </animation>
    
     <animation>
        <type>rotate</type>
        <object-name>switch_1_level (Meshed)</object-name>
        <property>fdm/jsbsim/systems/gauges/PHI/doppler/switch-terrain-sea-pos</property>
        <factor>-20</factor>
        <offset-deg>20.0</offset-deg>
        <center>
            <x-m> 0.0225</x-m>
            <y-m> 0.0</y-m>
            <z-m> 0.0</z-m>
        </center>
        <axis>
            <x>0</x>
            <y>-1</y>
            <z>0</z>
        </axis>
    </animation>
    
    <animation>
        <type>pick</type>
        <visible>true</visible>
        <object-name>switch_2_increase (Meshed)</object-name> 
        <action>
            <button>0</button>
            <repeatable>false</repeatable>
            <interval-sec>0.2</interval-sec>
            <binding>
                <command>property-assign</command>
                <property>fdm/jsbsim/systems/gauges/PHI/doppler/switch-increase</property>
                <value>1</value>
            </binding>
            <mod-up>
            <button>0</button>
                <binding>
                    <command>property-assign</command>
                    <property>fdm/jsbsim/systems/gauges/PHI/doppler/switch-increase</property>
                    <value>0</value>
                </binding>
            </mod-up>
        </action>
    </animation>
    
    <animation>
        <type>pick</type>
        <visible>true</visible>
        <object-name>switch_2_decrease (Meshed)</object-name> 
        <action>
            <button>0</button>
            <repeatable>false</repeatable>
            <interval-sec>0.2</interval-sec>
            <binding>
                <command>property-assign</command>
                <property>fdm/jsbsim/systems/gauges/PHI/doppler/switch-decrease</property>
                <value>1</value>
            </binding>
            <mod-up>
            <button>0</button>
                <binding>
                    <command>property-assign</command>
                    <property>fdm/jsbsim/systems/gauges/PHI/doppler/switch-decrease</property>
                    <value>0</value>
                </binding>
            </mod-up>
        </action>
    </animation>
    
    <animation>
        <type>pick</type>
        <visible>true</visible>
        <object-name>switch_2_left (Meshed)</object-name> 
        <action>
            <button>0</button>
            <repeatable>false</repeatable>
            <interval-sec>0.2</interval-sec>
            <binding>
                <command>property-assign</command>
                <property>fdm/jsbsim/systems/gauges/PHI/doppler/switch-left</property>
                <value>1</value>
            </binding>
            <mod-up>
            <button>0</button>
                <binding>
                    <command>property-assign</command>
                    <property>fdm/jsbsim/systems/gauges/PHI/doppler/switch-left</property>
                    <value>0</value>
                </binding>
            </mod-up>
        </action>
    </animation>
    
    <animation>
        <type>pick</type>
        <visible>true</visible>
        <object-name>switch_2_right (Meshed)</object-name> 
        <action>
            <button>0</button>
            <repeatable>false</repeatable>
            <interval-sec>0.2</interval-sec>
            <binding>
                <command>property-assign</command>
                <property>fdm/jsbsim/systems/gauges/PHI/doppler/switch-right</property>
                <value>1</value>
            </binding>
            <mod-up>
            <button>0</button>
                <binding>
                    <command>property-assign</command>
                    <property>fdm/jsbsim/systems/gauges/PHI/doppler/switch-right</property>
                    <value>0</value>
                </binding>
            </mod-up>
        </action>
    </animation>
    
    <animation>
        <type>rotate</type>
        <object-name>switch_2_level (Meshed)</object-name>
        <property>fdm/jsbsim/systems/gauges/PHI/doppler/switch-increase-pos</property>
        <factor>25</factor>
        <center>
            <x-m> 0.0225</x-m>
            <y-m> 0.0</y-m>
            <z-m> -0.004</z-m>
        </center>
        <axis>
            <x>0</x>
            <y>-1</y>
            <z>0</z>
        </axis>
    </animation>
    
    <animation>
        <type>rotate</type>
        <object-name>switch_2_level (Meshed)</object-name>
        <property>fdm/jsbsim/systems/gauges/PHI/doppler/switch-decrease-pos</property>
        <factor>25</factor>
        <center>
            <x-m> 0.0225</x-m>
            <y-m> 0.0</y-m>
            <z-m> -0.004</z-m>
        </center>
        <axis>
            <x>0</x>
            <y>1</y>
            <z>0</z>
        </axis>
    </animation>
    
    <animation>
        <type>rotate</type>
        <object-name>switch_2_level (Meshed)</object-name>
        <property>fdm/jsbsim/systems/gauges/PHI/doppler/switch-right-pos</property>
        <factor>25</factor>
        <center>
            <x-m> 0.0225</x-m>
            <y-m> -0.063</y-m>
            <z-m> -0.004</z-m>
        </center>
        <axis>
            <x>-1</x>
            <y>0</y>
            <z>0</z>
        </axis>
    </animation>
    
    <animation>
        <type>rotate</type>
        <object-name>switch_2_level (Meshed)</object-name>
        <property>fdm/jsbsim/systems/gauges/PHI/doppler/switch-left-pos</property>
        <factor>25</factor>
        <center>
            <x-m> 0.0225</x-m>
            <y-m> -0.063</y-m>
            <z-m> -0.004</z-m>
        </center>
        <axis>
            <x>1</x>
            <y>0</y>
            <z>0</z>
        </axis>
    </animation>
    
</PropertyList>
