<?xml version="1.0" encoding="ISO-8859-1"?>

<PropertyList>
    
    <path>PHI-Indicator.ac</path>
    
    <effect>
        <inherits-from>Effects/model-transparent</inherits-from>
        <object-name>glass (Meshed)</object-name>
    </effect>

    <effect>
        <inherits-from>Aircraft/G91-R1B_HD/Models/Effects/Interior_Shading/Interior_Shading</inherits-from>
        <object-name>screews_01 (Meshed)</object-name>
        <object-name>screews_02 (Meshed)</object-name>
        <object-name>screews_03 (Meshed)</object-name>
        <object-name>screews_04 (Meshed)</object-name>
        <object-name>screews_05 (Meshed)</object-name>
        <object-name>frontal (Meshed)</object-name>
        <object-name>back_frontal (Meshed)</object-name>
        <object-name>knob_001 (Meshed)</object-name>
        <object-name>knob_002 (Meshed)</object-name>
        <object-name>knob_003 (Meshed)</object-name>
        <object-name>knob_004 (Meshed)</object-name>
        <object-name>knob_001_A (Meshed)</object-name>
        <object-name>ring (Meshed)</object-name>
        <object-name>glass (Meshed)</object-name>
        <object-name>knob_001_plate_A (Meshed)</object-name>
        <object-name>knob_001_A_plate_A (Meshed)</object-name>
        <object-name>knob_002_plate_A (Meshed)</object-name>
        <object-name>knob_003_plate_A (Meshed)</object-name>
        <object-name>knob_004_plate_A (Meshed)</object-name>
        <object-name>frontal_mark_knob_001 (Meshed)</object-name>
        <object-name>NWE_ref (Meshed)</object-name>
        <object-name>frontal_border_plate_ABIS</object-name>
        <object-name>back_plate_B (Meshed)</object-name>
        <object-name>frontal_plate_A (Meshed)</object-name>
        <object-name>back_plate_A (Meshed)</object-name>
        <object-name>frontal_plate_B (Meshed)</object-name>
        <object-name>arrow_0 (Meshed)</object-name>
        <object-name>arrow_1 (Meshed)</object-name>
        <object-name>arrow_2 (Meshed)</object-name>
        <object-name>support (Meshed)</object-name>
        <object-name>axis (Meshed)</object-name>
        <object-name>airplane_support (Meshed)</object-name>
        <object-name>arrow_3 (Meshed)</object-name>
        <object-name>arrow_4 (Meshed)</object-name>
        <object-name>pointer_1_B (Meshed)</object-name>
        <object-name>frontal_plate_A (Meshed)</object-name>
    </effect>    

    <animation> 
        <type>material</type>
        <object-name>cover (Meshed)</object-name>
        <texture>Pictures/G91-Al-dark.png</texture>
        <ambient>
            <red>0.1</red>
            <green>0.1</green>
            <blue>0.1</blue>
        </ambient>
    </animation>
    
    <animation> 
        <type>material</type>
        <object-name>screews_01 (Meshed)</object-name>
        <object-name>screews_02 (Meshed)</object-name>
        <object-name>screews_03 (Meshed)</object-name>
        <object-name>screews_04 (Meshed)</object-name>
        <object-name>screews_05 (Meshed)</object-name>
        <texture>Pictures/G91-Dark-Grey.png</texture>
        <ambient>
            <red>0.6</red>
            <green>0.6</green>
            <blue>0.6</blue>
        </ambient>
    </animation>
    
    <animation> 
        <type>material</type>
        <object-name>frontal (Meshed)</object-name>
        <object-name>back_frontal (Meshed)</object-name>
        <texture>Pictures/G91-Al-dark.png</texture>
        <ambient>
            <red>0.6</red>
            <green>0.6</green>
            <blue>0.6</blue>
        </ambient>
        <emission>
            <red>0.2</red>
            <green>0.0</green>
            <blue>0.0</blue>
            <factor-prop>sim/G91/re_emit/gauge_red_light</factor-prop>
        </emission>
        <specular>
            <red>0.9</red>
            <green>0.9</green>
            <blue>0.9</blue>
        </specular>
    </animation>
    
    <animation> 
        <type>material</type>
        <object-name>knob_001 (Meshed)</object-name>
        <object-name>knob_002 (Meshed)</object-name>
        <object-name>knob_003 (Meshed)</object-name>
        <object-name>knob_004 (Meshed)</object-name>
        <texture>Pictures/G91-Dark-Grey.png</texture>
        <ambient>
            <red>0.6</red>
            <green>0.6</green>
            <blue>0.6</blue>
        </ambient>
        <emission>
            <red>0.05</red>
            <green>0.0</green>
            <blue>0.0</blue>
            <factor-prop>sim/G91/re_emit/gauge_red_light</factor-prop>
        </emission>
        <specular>
            <red>0.9</red>
            <green>0.9</green>
            <blue>0.9</blue>
        </specular>
    </animation>
    
    <animation> 
        <type>material</type>
        <object-name>knob_001_A (Meshed)</object-name>
        <texture>Pictures/G91-Dark-Grey.png</texture>
        <ambient>
            <red>0.7</red>
            <green>0.7</green>
            <blue>0.7</blue>
        </ambient>
        <emission>
            <red>0.10</red>
            <green>0.0</green>
            <blue>0.0</blue>
            <factor-prop>sim/G91/re_emit/gauge_red_light</factor-prop>
        </emission>
        <specular>
            <red>0.9</red>
            <green>0.9</green>
            <blue>0.9</blue>
        </specular>
    </animation>
    
    <animation> 
        <type>material</type>
        <object-name>ring (Meshed)</object-name>
        <texture>Pictures/G91-Dark-Grey.png</texture>
        <ambient>
            <red>0.3</red>
            <green>0.3</green>
            <blue>0.3</blue>
        </ambient>
    </animation>
    
    <animation> 
        <type>material</type>
        <object-name>glass (Meshed)</object-name>
        <texture>Pictures/G91-Al-Light.png</texture>
        <transparency>
            <alpha>0.2</alpha>
        </transparency>
        <ambient>
            <red>0.0</red>
            <green>0.0</green>
            <blue>0.0</blue>
        </ambient>
        <emission>
            <red>0.01</red>
            <green>0.07</green>
            <blue>0.0</blue>
            <factor-prop>sim/G91/re_emit/gauge_phosphorescent_light</factor-prop>
        </emission>
    </animation>
    
    <animation> 
        <type>material</type>
        <object-name>knob_001_plate_A (Meshed)</object-name>
        <object-name>knob_001_A_plate_A (Meshed)</object-name>
        <object-name>knob_002_plate_A (Meshed)</object-name>
        <object-name>knob_003_plate_A (Meshed)</object-name>
        <object-name>knob_004_plate_A (Meshed)</object-name>
        <object-name>frontal_mark_knob_001 (Meshed)</object-name>
        <transparency>
            <alpha>1.0</alpha>
        </transparency>
        <ambient>
            <red>0.80</red>
            <green>0.73</green>
            <blue>0.53</blue>
        </ambient>
        <emission>
            <red>0.045</red>
            <green>0.15</green>
            <blue>0.031</blue>
            <factor-prop>sim/G91/re_emit/gauge_phosphorescent_light</factor-prop>
        </emission>
    </animation>
    
    <animation> 
        <type>material</type>
        <object-name>NWE_ref (Meshed)</object-name>
        <transparency>
            <alpha>1.0</alpha>
        </transparency>
        <ambient>
            <red>0.80</red>
            <green>0.73</green>
            <blue>0.53</blue>
        </ambient>
        <emission>
            <red>0.025</red>
            <green>0.10</green>
            <blue>0.021</blue>
            <factor-prop>sim/G91/re_emit/gauge_phosphorescent_light</factor-prop>
        </emission>
    </animation>
    
    <animation> 
        <type>material</type>
        <object-name>frontal_border_plate_ABIS</object-name>
        <transparency>
            <alpha>1.0</alpha>
        </transparency>
        <ambient>
            <red>0.80</red>
            <green>0.73</green>
            <blue>0.53</blue>
        </ambient>
        <emission>
            <red>0.045</red>
            <green>0.15</green>
            <blue>0.031</blue>
            <factor-prop>sim/G91/re_emit/gauge_phosphorescent_light</factor-prop>
        </emission>
    </animation>
    
    <animation> 
        <type>material</type>
        <object-name>back_plate_B (Meshed)</object-name>
        <texture>Pictures/G91-Dark-Grey.png</texture>
        <ambient>
            <red>0.0</red>
            <green>0.0</green>
            <blue>0.0</blue>
        </ambient>
        <emission>
            <red>0.25</red>
            <green>0.0</green>
            <blue>0.0</blue>
            <factor-prop>sim/G91/re_emit/gauge_red_light</factor-prop>
        </emission>
    </animation>
    
    <animation> 
        <type>material</type>
        <object-name>frontal_plate_A (Meshed)</object-name>
        <object-name>back_plate_A (Meshed)</object-name>
        <transparency>
            <alpha>1.0</alpha>
        </transparency>
        <ambient>
            <red>0.90</red>
            <green>0.83</green>
            <blue>0.63</blue>
        </ambient>
        <emission>
            <red>0.045</red>
            <green>0.15</green>
            <blue>0.031</blue>
            <factor-prop>sim/G91/re_emit/gauge_phosphorescent_light</factor-prop>
        </emission>
    </animation>
    
    <animation> 
        <type>material</type>
        <object-name>frontal_plate_B (Meshed)</object-name>
        <texture>Pictures/G91-Dark-Grey.png</texture>
        <ambient>
            <red>0.0</red>
            <green>0.0</green>
            <blue>0.0</blue>
        </ambient>
        <emission>
            <red>0.30</red>
            <green>0.0</green>
            <blue>0.0</blue>
            <factor-prop>sim/G91/re_emit/gauge_red_light</factor-prop>
        </emission>
    </animation>
    
    <animation>
        <type>material</type>
        <object-name>arrow_0 (Meshed)</object-name>
        <object-name>arrow_1 (Meshed)</object-name>
        <transparency>
            <alpha>1.0</alpha>
        </transparency>
        <ambient>
            <red>0.90</red>
            <green>0.83</green>
            <blue>0.63</blue>
        </ambient>
        <emission>
            <red>0.045</red>
            <green>0.25</green>
            <blue>0.031</blue>
            <factor-prop>sim/G91/re_emit/gauge_phosphorescent_light</factor-prop>
        </emission>
    </animation>
    
    <animation>
        <type>material</type>
        <object-name>arrow_2 (Meshed)</object-name>
        <object-name>support (Meshed)</object-name>
        <object-name>axis (Meshed)</object-name>
        <object-name>airplane_support (Meshed)</object-name>
        <texture>Pictures/G91-Dark-Grey.png</texture>
        <ambient>
            <red>0.0</red>
            <green>0.0</green>
            <blue>0.0</blue>
        </ambient>
        <emission>
            <red>0.30</red>
            <green>0.0</green>
            <blue>0.0</blue>
            <factor-prop>sim/G91/re_emit/gauge_red_light</factor-prop>
        </emission>
    </animation>
    
    <animation>
        <type>material</type>
        <object-name>arrow_3 (Meshed)</object-name>
        <object-name>arrow_4 (Meshed)</object-name>
        <transparency>
            <alpha>1.0</alpha>
        </transparency>
        <ambient>
            <red>0.90</red>
            <green>0.83</green>
            <blue>0.63</blue>
        </ambient>
        <emission>
            <red>0.045</red>
            <green>0.25</green>
            <blue>0.031</blue>
            <factor-prop>sim/G91/re_emit/gauge_phosphorescent_light</factor-prop>
        </emission>
    </animation>
    
    <animation> 
        <type>material</type>
        <object-name>pointer_1_B (Meshed)</object-name>
        <texture>Pictures/G91-Dark-Grey.png</texture>
        <ambient>
            <red>0.2</red>
            <green>0.2</green>
            <blue>0.2</blue>
        </ambient>
        <emission>
            <red>0.1</red>
            <green>0.0</green>
            <blue>0.0</blue>
            <factor-prop>sim/G91/re_emit/gauge_red_light</factor-prop>
        </emission>
    </animation>
    
    <animation>
        <type>rotate</type>
        <object-name>frontal_plate_A (Meshed)</object-name>
        <property>/instrumentation/heading-indicator/indicated-heading-deg</property>
        <axis>
            <x>  1 </x>
            <y>  0 </y>
            <z>  0 </z>
        </axis>
    </animation>
    
    <model>
        <name>procedural_light_cockpit_gauge_spot_red</name>
        <path>Aircraft/G91-R1B_HD/Models/Parts/Cockpit/Effects/lights/procedural_light_cockpit_gauge_spot_red.xml</path>
        <offsets>
            <x-m> 0.03</x-m>
            <y-m> 0.0 </y-m>
            <z-m> 0.0 </z-m>
        </offsets>
    </model>

</PropertyList>
